{
  "$schema": "https://developer.microsoft.com/json-schemas/fabric/item/report/definition/visualContainer/2.1.0/schema.json",
  "name": "d62999e57395d46ed9bc",
  "position": {
    "x": 16.785562298053431,
    "y": 139.44928678382851,
    "z": 4000,
    "height": 179.47639687918669,
    "width": 140.74048388367876,
    "tabOrder": 4000
  },
  "visual": {
    "visualType": "textbox",
    "objects": {
      "general": [
        {
          "properties": {
            "paragraphs": [
              {
                "textRuns": [
                  {
                    "value": "Progetti il cui avanzamento dei costi delle attività di supervisione del personale impiegato nelle attività di ",
                    "textStyle": {
                      "fontFamily": "DIN Light",
                      "fontSize": "9pt"
                    }
                  },
                  {
                    "value": "construction / fabrication",
                    "textStyle": {
                      "fontFamily": "DIN Light",
                      "fontStyle": "italic",
                      "fontSize": "9pt"
                    }
                  },
                  {
                    "value": " è",
                    "textStyle": {
                      "fontFamily": "DIN Light",
                      "fontSize": "9pt"
                    }
                  }
                ]
              },
              {
                "textRuns": [
                  {
                    "value": "superiore all’avanzamento dei costi relativi alle attività di ",
                    "textStyle": {
                      "fontFamily": "DIN Light",
                      "fontSize": "9pt"
                    }
                  },
                  {
                    "value": "construction /fabrication",
                    "textStyle": {
                      "fontFamily": "DIN Light",
                      "fontStyle": "italic",
                      "fontSize": "9pt"
                    }
                  },
                  {
                    "value": " ",
                    "textStyle": {
                      "fontFamily": "DIN Light",
                      "fontSize": "9pt"
                    }
                  }
                ]
              },
              {
                "textRuns": [
                  {
                    "value": ""
                  }
                ]
              }
            ]
          }
        }
      ]
    },
    "drillFilterOtherVisuals": true
  }
}