{
  "$schema": "https://developer.microsoft.com/json-schemas/fabric/item/report/definition/visualContainer/2.1.0/schema.json",
  "name": "592ea9209076eb82a233",
  "position": {
    "x": 355.83333333333337,
    "y": 125,
    "z": 14000,
    "height": 56,
    "width": 102.5,
    "tabOrder": 13000
  },
  "visual": {
    "visualType": "cardVisual",
    "query": {
      "queryState": {
        "Data": {
          "projections": [
            {
              "field": {
                "Measure": {
                  "Expression": {
                    "SourceRef": {
                      "Entity": "_MISURE"
                    }
                  },
                  "Property": "CountProgetti"
                }
              },
              "queryRef": "_MISURE.CountProgetti",
              "nativeQueryRef": "CountProgetti"
            }
          ]
        }
      },
      "sortDefinition": {
        "sort": [
          {
            "field": {
              "Measure": {
                "Expression": {
                  "SourceRef": {
                    "Entity": "_MISURE"
                  }
                },
                "Property": "CountProgetti"
              }
            },
            "direction": "Descending"
          }
        ],
        "isDefaultSort": true
      }
    },
    "objects": {
      "fillCustom": [
        {
          "properties": {
            "show": {
              "expr": {
                "Literal": {
                  "Value": "false"
                }
              }
            }
          }
        }
      ],
      "outline": [
        {
          "properties": {
            "show": {
              "expr": {
                "Literal": {
                  "Value": "false"
                }
              }
            }
          },
          "selector": {
            "id": "default"
          }
        }
      ],
      "value": [
        {
          "properties": {
            "fontSize": {
              "expr": {
                "Literal": {
                  "Value": "17D"
                }
              }
            },
            "fontColor": {
              "solid": {
                "color": {
                  "expr": {
                    "Literal": {
                      "Value": "'#E98300'"
                    }
                  }
                }
              }
            },
            "horizontalAlignment": {
              "expr": {
                "Literal": {
                  "Value": "'center'"
                }
              }
            }
          },
          "selector": {
            "metadata": "_MISURE.CountProgetti"
          }
        }
      ],
      "label": [
        {
          "properties": {
            "text": {
              "expr": {
                "Literal": {
                  "Value": "'Early Phase'"
                }
              }
            },
            "fontSize": {
              "expr": {
                "Literal": {
                  "Value": "8D"
                }
              }
            },
            "fontColor": {
              "solid": {
                "color": {
                  "expr": {
                    "ThemeDataColor": {
                      "ColorId": 1,
                      "Percent": 0.4
                    }
                  }
                }
              }
            },
            "position": {
              "expr": {
                "Literal": {
                  "Value": "'belowValue'"
                }
              }
            }
          },
          "selector": {
            "metadata": "_MISURE.CountProgetti"
          }
        }
      ],
      "spacing": [
        {
          "properties": {
            "verticalSpacing": {
              "expr": {
                "Literal": {
                  "Value": "2L"
                }
              }
            }
          },
          "selector": {
            "metadata": "_MISURE.CountProgetti"
          }
        }
      ],
      "padding": [
        {
          "properties": {
            "paddingSelection": {
              "expr": {
                "Literal": {
                  "Value": "'Custom'"
                }
              }
            }
          },
          "selector": {
            "id": "default"
          }
        }
      ]
    },
    "visualContainerObjects": {
      "title": [
        {
          "properties": {
            "titleWrap": {
              "expr": {
                "Literal": {
                  "Value": "true"
                }
              }
            }
          }
        }
      ],
      "background": [
        {
          "properties": {
            "show": {
              "expr": {
                "Literal": {
                  "Value": "true"
                }
              }
            },
            "transparency": {
              "expr": {
                "Literal": {
                  "Value": "100D"
                }
              }
            }
          }
        }
      ],
      "visualHeader": [
        {
          "properties": {
            "show": {
              "expr": {
                "Literal": {
                  "Value": "false"
                }
              }
            }
          }
        }
      ]
    },
    "drillFilterOtherVisuals": true
  },
  "filterConfig": {
    "filters": [
      {
        "name": "Filterd7dd54489a0c64c1ee53",
        "ordinal": 0,
        "field": {
          "Column": {
            "Expression": {
              "SourceRef": {
                "Entity": "PSR_Card_Consolidated"
              }
            },
            "Property": "_Cluster_Progress"
          }
        },
        "type": "Categorical",
        "filter": {
          "Version": 2,
          "From": [
            {
              "Name": "p",
              "Entity": "PSR_Card_Consolidated",
              "Type": 0
            }
          ],
          "Where": [
            {
              "Condition": {
                "In": {
                  "Expressions": [
                    {
                      "Column": {
                        "Expression": {
                          "SourceRef": {
                            "Source": "p"
                          }
                        },
                        "Property": "_Cluster_Progress"
                      }
                    }
                  ],
                  "Values": [
                    [
                      {
                        "Literal": {
                          "Value": "' Early Phase'"
                        }
                      }
                    ]
                  ]
                }
              }
            }
          ]
        },
        "howCreated": "User",
        "isHiddenInViewMode": true,
        "isLockedInViewMode": true
      },
      {
        "name": "f15d6bb6510c60501960",
        "ordinal": 1,
        "field": {
          "Column": {
            "Expression": {
              "SourceRef": {
                "Entity": "Calculation group"
              }
            },
            "Property": "Calculation group column"
          }
        },
        "type": "Categorical",
        "filter": {
          "Version": 2,
          "From": [
            {
              "Name": "c",
              "Entity": "Calculation group",
              "Type": 0
            }
          ],
          "Where": [
            {
              "Condition": {
                "In": {
                  "Expressions": [
                    {
                      "Column": {
                        "Expression": {
                          "SourceRef": {
                            "Source": "c"
                          }
                        },
                        "Property": "Calculation group column"
                      }
                    }
                  ],
                  "Values": [
                    [
                      {
                        "Literal": {
                          "Value": "'_Ultimo_forecast'"
                        }
                      }
                    ]
                  ]
                }
              }
            }
          ]
        },
        "howCreated": "User",
        "isHiddenInViewMode": true,
        "isLockedInViewMode": true
      },
      {
        "name": "5ad555cbe6de5ce0ab8e",
        "ordinal": 2,
        "field": {
          "Measure": {
            "Expression": {
              "SourceRef": {
                "Entity": "_MISURE"
              }
            },
            "Property": "CountProgetti"
          }
        },
        "type": "Advanced",
        "isHiddenInViewMode": true,
        "isLockedInViewMode": true
      }
    ],
    "filterSortOrder": "Custom"
  }
}